setup.py
distafra/Binomialdistribution.py
distafra/Gaussiandistribution.py
distafra/Generaldistribution.py
distafra/__init__.py
distafra.egg-info/PKG-INFO
distafra.egg-info/SOURCES.txt
distafra.egg-info/dependency_links.txt
distafra.egg-info/not-zip-safe
distafra.egg-info/top_level.txt