Metadata-Version: 1.0
Name: distafra
Version: 0.1
Summary: Gaussian distributions
Home-page: UNKNOWN
Author: Arfa
Author-email: arfat2396@gmail.com
License: UNKNOWN
Platform: UNKNOWN
